ChengxushejiSixiangYuFangfa/README.md
ChengxushejiSixiangYuFangfa/__init__.py
ChengxushejiSixiangYuFangfa/__main__.py
ChengxushejiSixiangYuFangfa/file.epub
ChengxushejiSixiangYuFangfa/index.html
ChengxushejiSixiangYuFangfa/css/__init__.py
ChengxushejiSixiangYuFangfa/css/annotations.css
ChengxushejiSixiangYuFangfa/css/main.css
ChengxushejiSixiangYuFangfa/css/normalize.css
ChengxushejiSixiangYuFangfa/css/popup.css
ChengxushejiSixiangYuFangfa/font/__init__.py
ChengxushejiSixiangYuFangfa/font/fontello.eot
ChengxushejiSixiangYuFangfa/font/fontello.svg
ChengxushejiSixiangYuFangfa/font/fontello.ttf
ChengxushejiSixiangYuFangfa/font/fontello.woff
ChengxushejiSixiangYuFangfa/img/__init__.py
ChengxushejiSixiangYuFangfa/img/annotator-glyph-sprite.png
ChengxushejiSixiangYuFangfa/img/annotator-icon-sprite.png
ChengxushejiSixiangYuFangfa/img/apple-touch-icon.png
ChengxushejiSixiangYuFangfa/img/cancelfullscreen.png
ChengxushejiSixiangYuFangfa/img/close.png
ChengxushejiSixiangYuFangfa/img/fullscreen.png
ChengxushejiSixiangYuFangfa/img/loader.gif
ChengxushejiSixiangYuFangfa/img/menu-icon.png
ChengxushejiSixiangYuFangfa/img/save.png
ChengxushejiSixiangYuFangfa/img/saved.png
ChengxushejiSixiangYuFangfa/img/settings-s.png
ChengxushejiSixiangYuFangfa/img/settings.png
ChengxushejiSixiangYuFangfa/img/star.png
ChengxushejiSixiangYuFangfa/js/__init__.py
ChengxushejiSixiangYuFangfa/js/epub.js
ChengxushejiSixiangYuFangfa/js/epub.min.js
ChengxushejiSixiangYuFangfa/js/epub.min.map
ChengxushejiSixiangYuFangfa/js/hooks.min.js
ChengxushejiSixiangYuFangfa/js/hooks.min.map
ChengxushejiSixiangYuFangfa/js/reader.js
ChengxushejiSixiangYuFangfa/js/reader.js.map
ChengxushejiSixiangYuFangfa/js/reader.min.js
ChengxushejiSixiangYuFangfa/js/reader.min.map
ChengxushejiSixiangYuFangfa/js/hooks/__init__.py
ChengxushejiSixiangYuFangfa/js/hooks/extensions/__init__.py
ChengxushejiSixiangYuFangfa/js/hooks/extensions/highlight.js
ChengxushejiSixiangYuFangfa/js/libs/__init__.py
chengxusheji_sixiang_yu_fangfa-2024.3.2.0.dist-info/METADATA
chengxusheji_sixiang_yu_fangfa-2024.3.2.0.dist-info/WHEEL
chengxusheji_sixiang_yu_fangfa-2024.3.2.0.dist-info/entry_points.txt
chengxusheji_sixiang_yu_fangfa-2024.3.2.0.dist-info/top_level.txt
chengxusheji_sixiang_yu_fangfa-2024.3.2.0.dist-info/RECORD
